{
    "白苔": {
        "病因": "白苔是指舌面上出现一层白色浊腻苔，苔质致密，颗粒细小，不易刮脱的舌象。其形成主要与感受寒湿之邪、饮食不节等因素相关。基本病机为湿浊上泛，发于舌苔。病位在舌，与脾胃等脏腑关系密切。具体病因包括：1) 汗出受寒、冒雨涉水等感受寒湿之邪；2) 过食生冷或黏腻食物损伤脾胃，导致脾阳不振，水湿凝聚为痰饮上泛。",
        "症状": {
            "典型表现": "舌面上出现一层白色浊腻苔，主要表现在：1) 苔质致密，颗粒细腻，舌边苔薄，舌中苔厚，刮之难去；2) 舌苔色白，有薄、厚之分（透过白苔可见舌体为薄白苔，舌体被遮盖为厚白苔）。根据临床分类表现不同：1) 外感寒湿：舌苔薄白膩，伴发热怕冷、头痛身重；2) 湿阻膜原：舌苔白厚腻而干或厚如积粉，舌质红，伴发热怕冷、手足沉重；3) 寒饮内停：舌苔白腻水滑，舌质青紫，伴面色苍白、呕吐清涎。",
            "伴随症状": "1) 外感症状：发热怕冷、头痛身重、无汗；2) 消化系统症状：恶心呕吐、胃脘胀满；3) 全身症状：手足沉重、四肢乏力、神情倦怠；4) 其他：口不渴或渴不欲饮、小便少。"
        },
        "治疗": {
            "中医治疗": "辨证施治：1) 外感寒湿：温散寒湿，用羌活胜湿汤（川芎、羌活、防风等）；2) 湿阻膜原：开达膜原辟移化浊，用达原饮（槟榔、厚朴、黄芩等）；3) 寒饮内停：温阳醒脾行水，用温脾汤（制附子、干姜、大黄等）。中成药可选小青龙合剂、苏子降气丸等。",
            "西医治疗": "1) 针对原发病因治疗；2) 实验室检查异常指标的对症处理；3) 必要时补充维生素或微量元素。",
            "其他疗法": "按摩疗法：揉按阴陵泉穴，每日2次，每次1-3分钟。"
        },
        "预防": {
            "生活方式": "1) 保持居室干燥通风，避免久居湿地；2) 作息规律，注意防寒保暖；3) 劳逸结合，避免汗出当风；4) 加强体育锻炼增强体质；5) 保持口腔清洁，用淡盐水漱口。",
            "饮食调理": "1) 饮食宜软、热、清淡易消化；2) 多食温性食物（小米粥、山药粥等）；3) 忌食生冷（冰饮）、油腻（油炸食品）、过甜过咸食物；4) 少食多餐，避免暴饮暴食。"
        },
        "就医指南": {
            "就诊指征": "1) 舌面持续出现白色浊腻苔不易刮脱；2) 伴随发热怕冷、身体疼痛、手足沉重等症状。",
            "就诊科室": "中医科",
            "检查准备": "1) 就诊前清淡饮食；2) 避免食用会使舌苔染色的食物（牛奶、豆浆等）；3) 携带既往病历和检查报告。",
            "医患问答": {
                "医生可能询问": ["症状持续时间", "加重/缓解因素", "生活环境", "饮食习惯", "既往病史"],
                "患者可以咨询": ["病因诊断", "治疗方案", "用药注意事项", "康复护理", "复诊安排"]
            }
        },
        "预后": {
            "一般预后": "早期调理得当可恢复正常；延误治疗可能导致阳气虚衰、脏腑损伤。",
            "复发因素": "病因未根除或调护不当可能复发。"
        }
    }
}